nn_trainer/__init__.py
nn_trainer/callbacks.py
nn_trainer/logger.py
nn_trainer/metrics.py
nn_trainer/utils.py
nn_trainer/data/__init__.py
nn_trainer/data/circle_data_set.py
nn_trainer/data/data_set.py
nn_trainer/data/mnist_data_set.py
nn_trainer/models/RaUnet.py
nn_trainer/models/__init__.py
nn_trainer/models/networks/__init__.py
nn_trainer/models/networks/networks_1d.py
nn_trainer/models/networks/networks_2d.py
nn_trainer/models/resnet/__init__.py
nn_trainer/models/resnet/parts.py
nn_trainer/models/unet/__init__.py
nn_trainer/models/unet/parts.py
nn_trainer/plotters/__init__.py
nn_trainer/plotters/abstract_data_plotter.py
nn_trainer/plotters/bar_chart_data_plotter.py
nn_trainer/plotters/image_data_plotter.py
nn_trainer/plotters/line_chart_data_plotter.py
nn_trainer/plotters/scatter_plot_data_plotter.py
nn_trainer/trainers/__init__.py
nn_trainer/trainers/abstract_nn_trainer.py
nn_trainer/trainers/basic_nn_trainer.py
nn_trainer/trainers/vanilla_gan_nn_trainer.py
nn_trainer/trainers/wasserstein_gan_nn_trainer.py
nn_trainer-0.0.3.7.dist-info/LICENSE
nn_trainer-0.0.3.7.dist-info/METADATA
nn_trainer-0.0.3.7.dist-info/WHEEL
nn_trainer-0.0.3.7.dist-info/top_level.txt
nn_trainer-0.0.3.7.dist-info/RECORD
